<DOMSymbolItem xmlns:xsi="http://www.w3.org/2001/XMLSchema-instance" xmlns="http://ns.adobe.com/xfl/2008/" name="Expt Assets/TC_TObject__Callout2a" itemID="5baa9460-000005d8" lastModified="1537905760" lastUniqueIdentifier="1">
  <timeline>
    <DOMTimeline name="TC_TObject__Callout2a">
      <layers>
        <DOMLayer name="Layer_1" color="#00FFFF" current="true" isSelected="true">
          <frames>
            <DOMFrame index="0" keyMode="9728">
              <elements>
                <DOMSymbolInstance libraryItemName="Expt Assets/TC_TObject__Callout" selected="true">
                  <matrix>
                    <Matrix tx="107.25" ty="5.8"/>
                  </matrix>
                  <transformationPoint>
                    <Point x="32.65" y="15.65"/>
                  </transformationPoint>
                </DOMSymbolInstance>
                <DOMDynamicText selected="true" fontRenderingMode="standard" width="100" height="38.2" isSelectable="false" lineType="multiline">
                  <matrix>
                    <Matrix tx="2" ty="2"/>
                  </matrix>
                  <textRuns>
                    <DOMTextRun>
                      <characters>Music Amount:&#xD;Constant Music</characters>
                      <textAttrs>
                        <DOMTextAttrs alignment="center" aliasText="false" autoKern="false" lineHeight="18.1" size="14" bitmapSize="280" face="PTSans-Bold"/>
                      </textAttrs>
                    </DOMTextRun>
                  </textRuns>
                </DOMDynamicText>
              </elements>
            </DOMFrame>
          </frames>
        </DOMLayer>
      </layers>
    </DOMTimeline>
  </timeline>
</DOMSymbolItem>